[{"id":1,"title":"producto1","description":"descripcion1","price":1500,"thumbnail":"imagen1","code":"abc123","stock":51},{"id":2,"title":"producto2","description":"descripcion2","price":2500,"thumbnail":"imagen2","code":"def234","stock":42},{"id":3,"title":"producto3","description":"descripcion3","price":4500,"thumbnail":"imagen3","code":"ghi456","stock":35},{"id":4,"title":"producto4","description":"descripcion4","price":5500,"thumbnail":"imagen4","code":"jkl789","stock":24},{"id":5,"title":"producto5","description":"descripcion5","price":6500,"thumbnail":"imagen5","code":"mno987","stock":15},{"id":6,"title":"producto6","description":"descripcion6","price":8500,"thumbnail":"imagen6","code":"pqr765","stock":44},{"id":7,"title":"producto7","description":"descripcion7","price":9500,"thumbnail":"imagen7","code":"stu432","stock":77},{"id":8,"title":"producto8","description":"descripcion8","price":11500,"thumbnail":"imagen8","code":"vwx109","stock":64},{"id":9,"title":"producto9","description":"descripcion9","price":13500,"thumbnail":"imagen9","code":"yza159","stock":56},{"id":10,"title":"producto10","description":"descripcion10","price":17500,"thumbnail":"imagen10","code":"asd268","stock":99}]